{
  "build": {
    "beforeDevCommand": "npm run dev",
    "beforeBuildCommand": "npm run build",
    "frontendDist": "../build",
    "devUrl": "http://localhost:1420"
  },
  "bundle": {
    "active": true,
    "targets": "all",
    "category": "Utility",
    "icon": [
      "icons/icon.ico"
    ]
  },
  "productName": "DLsite Manager",
  "version": "2.0.0",
  "identifier": "dev.ashrimp.dlsite-manager",
  "plugins": {},
  "app": {
    "withGlobalTauri": false,
    "windows": [],
    "security": {
      "csp": null
    }
  }
}